calculator/__init__.py
calculator/__main__.py
calculator/server.py
calculator/core/__init__.py
calculator/core/advanced.py
calculator/core/basic.py
calculator/core/calculus.py
calculator/core/complex.py
calculator/core/constants.py
calculator/core/currency.py
calculator/core/financial.py
calculator/core/matrix.py
calculator/core/solver.py
calculator/core/statistics.py
calculator/core/tool_filter.py
calculator/core/tool_groups.py
calculator/core/units.py
calculator/core/validators.py
calculator/core/base/__init__.py
calculator/core/base/operation.py
calculator/core/base/service.py
calculator/core/base/validator.py
calculator/core/config/__init__.py
calculator/core/config/loader.py
calculator/core/config/settings.py
calculator/core/errors/__init__.py
calculator/core/errors/exceptions.py
calculator/core/errors/handlers.py
calculator/core/monitoring/__init__.py
calculator/core/monitoring/logging.py
calculator/core/monitoring/metrics.py
calculator/core/quality/__init__.py
calculator/core/quality/metrics.py
calculator/core/security/__init__.py
calculator/core/security/audit.py
calculator/core/security/rate_limiting.py
calculator/core/security/validation.py
calculator/models/__init__.py
calculator/models/errors.py
calculator/models/request.py
calculator/models/response.py
calculator/repositories/__init__.py
calculator/repositories/base.py
calculator/repositories/cache.py
calculator/repositories/constants.py
calculator/repositories/currency.py
calculator/server/__init__.py
calculator/server/app.py
calculator/server/compatibility.py
calculator/server/factory.py
calculator/server/health.py
calculator/server/middleware.py
calculator/server/handlers/__init__.py
calculator/server/handlers/arithmetic.py
calculator/services/__init__.py
calculator/services/arithmetic.py
calculator/services/base.py
calculator/services/cache.py
calculator/services/config.py
calculator/services/matrix.py
calculator/services/statistics.py
calculator/services/calculus/__init__.py
p6plab_mcp_calculator-2.0.1.dist-info/METADATA
p6plab_mcp_calculator-2.0.1.dist-info/WHEEL
p6plab_mcp_calculator-2.0.1.dist-info/entry_points.txt
p6plab_mcp_calculator-2.0.1.dist-info/licenses/LICENSE
p6plab_mcp_calculator-2.0.1.dist-info/RECORD
