Metadata-Version: 2.4
Name: p6plab-mcp-calculator
Version: 2.0.1
Summary: Scientific Calculator MCP Server - Comprehensive mathematical computation service for AI assistants
Project-URL: Homepage, https://github.com/peepeepopapapeepeepo/mcp-calculator
Project-URL: Repository, https://github.com/peepeepopapapeepeepo/mcp-calculator
Project-URL: Issues, https://github.com/peepeepopapapeepeepo/mcp-calculator/issues
Project-URL: Documentation, https://github.com/peepeepopapapeepeepo/mcp-calculator/blob/main/README.md
Project-URL: Changelog, https://github.com/peepeepopapapeepeepo/mcp-calculator/blob/main/CHANGELOG.md
Author-email: MCP Calculator Team <peepeepopapapeepeepo@gmail.com>
Maintainer-email: MCP Calculator Team <peepeepopapapeepeepo@gmail.com>
License: MIT License
License-File: LICENSE
Keywords: calculator,calculus,linear-algebra,mathematics,mcp,model-context-protocol,scientific-computing,statistics
Classifier: Development Status :: 5 - Production/Stable
Classifier: Intended Audience :: Developers
Classifier: Intended Audience :: Science/Research
Classifier: License :: OSI Approved :: MIT License
Classifier: Operating System :: OS Independent
Classifier: Programming Language :: Python :: 3
Classifier: Programming Language :: Python :: 3.8
Classifier: Programming Language :: Python :: 3.9
Classifier: Programming Language :: Python :: 3.10
Classifier: Programming Language :: Python :: 3.11
Classifier: Programming Language :: Python :: 3.12
Classifier: Topic :: Communications
Classifier: Topic :: Scientific/Engineering :: Mathematics
Classifier: Topic :: Software Development :: Libraries :: Python Modules
Requires-Python: >=3.8
Requires-Dist: fastmcp>=2.0.0
Requires-Dist: loguru>=0.6.0
Requires-Dist: numpy>=1.21.0
Requires-Dist: pydantic>=2.0.0
Requires-Dist: scipy>=1.7.0
Requires-Dist: sympy>=1.9.0
Provides-Extra: currency
Requires-Dist: requests>=2.25.0; extra == 'currency'
Provides-Extra: dev
Requires-Dist: bandit>=1.7.0; extra == 'dev'
Requires-Dist: build>=0.10.0; extra == 'dev'
Requires-Dist: pyright>=1.1.0; extra == 'dev'
Requires-Dist: pytest-asyncio>=0.21.0; extra == 'dev'
Requires-Dist: pytest-cov>=4.0.0; extra == 'dev'
Requires-Dist: pytest>=7.0.0; extra == 'dev'
Requires-Dist: ruff>=0.1.0; extra == 'dev'
Requires-Dist: twine>=4.0.0; extra == 'dev'
